shdwdb/__init__.py
shdwdb-0.0.10.dist-info/LICENSE
shdwdb-0.0.10.dist-info/METADATA
shdwdb-0.0.10.dist-info/WHEEL
shdwdb-0.0.10.dist-info/top_level.txt
shdwdb-0.0.10.dist-info/RECORD
