Metadata-Version: 2.1
Name: shdwdb
Version: 0.0.10
Summary: a package for tables
Home-page: https://github.com/shibby360/shdwdb
Author: shibby360
Author-email: shibby360 <shivank.chhaya@gmail.com>
License: MIT
Project-URL: Homepage, https://github.com/yourusername/your_package
Requires-Python: >=3.8.18
License-File: LICENSE
